{
    "palette-name": "Golden Twilight",
    "version": "1.0.0",
    "author": "Coolors.co",
    "date-created": "2025-12-21",
    "collection": {
        "file-name": "golden-twilight-colors.json",
        "schema-file": "color-file-schema.json",
        "description": "Collection of colors from the Golden Twilight palette",
        "color-files": [
            {
                "file-path": "color-files/ink-black.json",
                "color-family": "Black Shades"
            },
            {
                "file-path": "color-files/prussian-blue.json",
                "color-family": "Blue Shades"
            },
            {
                "file-path": "color-files/regal-navy.json",
                "color-family": "Blue Shades"
            },
            {
                "file-path": "color-files/school-bus-yellow.json",
                "color-family": "Yellow Shades"
            },
            {
                "file-path": "color-files/gold.json",
                "color-family": "Yellow Shades"
            }
        ]
    },
    "project-name": "Coolors Palettes",
    "project-url": "https://coolors.co",
    "description": "Color palette: Golden Twilight"
}