[
    {
        "unique-color-id": "14871275",
        "name": "Bit Of Blue",
        "other-names": [
            {
                "name": "Bit Of Blue",
                "source": {
                    "name": "Pantone",
                    "url": "http://www.pantone.com"
                }
            },
            {
                "name": "11-4601",
                "source": {
                    "name": "pantone-number",
                    "url": "http://www.pantone.com"
                }
            },
            {
                "name": "Aquafir",
                "source": {
                    "name": "color.pizza",
                    "url": "https://github.com/meodai/color-names"
                }
            }
        ],
        "naming-source": "Pantone",
        "nickname": "",
        "color-family": "Blue Shades",
        "color-codes": {
            "hex": {
                "values": {
                    "r1": "E",
                    "r2": "2",
                    "g1": "E",
                    "g2": "A",
                    "b1": "E",
                    "b2": "B",
                    "a1": "0",
                    "a2": "0"
                }
            },
            "rgb": {
                "values": {
                    "r": 226,
                    "g": 234,
                    "b": 235
                }
            },
            "hsl": {
                "values": {
                    "h": 187,
                    "s": 18,
                    "l": 90
                }
            },
            "cmyk": {
                "values": {
                    "c": 4,
                    "m": 0,
                    "y": 0,
                    "k": 8
                }
            }
        },
        "description": "A very light, muted blue with cool cyan-blue tones."
    }
]
