[
    {
        "unique-color-id": "12891814",
        "name": "Cement",
        "other-names": [
            {
                "name": "Cement",
                "source": {
                    "name": "Pantone",
                    "url": "http://www.pantone.com"
                }
            },
            {
                "name": "14-0708",
                "source": {
                    "name": "pantone-number",
                    "url": "http://www.pantone.com"
                }
            },
            {
                "name": "Esoteric",
                "source": {
                    "name": "color.pizza",
                    "url": "https://github.com/meodai/color-names"
                }
            }
        ],
        "naming-source": "Pantone",
        "nickname": "",
        "color-family": "Orange Shades",
        "color-codes": {
            "hex": {
                "values": {
                    "r1": "C",
                    "r2": "4",
                    "g1": "B",
                    "g2": "6",
                    "b1": "A",
                    "b2": "6",
                    "a1": "0",
                    "a2": "0"
                }
            },
            "rgb": {
                "values": {
                    "r": 196,
                    "g": 182,
                    "b": 166
                }
            },
            "hsl": {
                "values": {
                    "h": 32,
                    "s": 20,
                    "l": 71
                }
            },
            "cmyk": {
                "values": {
                    "c": 0,
                    "m": 7,
                    "y": 15,
                    "k": 23
                }
            }
        },
        "description": "A light, muted orange with warm orange-yellow tones."
    }
]
