[
    {
        "unique-color-id": "15854794",
        "name": "Ethereal Green",
        "other-names": [
            {
                "name": "Ethereal Green",
                "source": {
                    "name": "Pantone",
                    "url": "http://www.pantone.com"
                }
            },
            {
                "name": "11-0609",
                "source": {
                    "name": "pantone-number",
                    "url": "http://www.pantone.com"
                }
            },
            {
                "name": "Natural Light",
                "source": {
                    "name": "color.pizza",
                    "url": "https://github.com/meodai/color-names"
                }
            }
        ],
        "naming-source": "Pantone",
        "nickname": "",
        "color-family": "Yellow Shades",
        "color-codes": {
            "hex": {
                "values": {
                    "r1": "F",
                    "r2": "1",
                    "g1": "E",
                    "g2": "C",
                    "b1": "C",
                    "b2": "A",
                    "a1": "0",
                    "a2": "0"
                }
            },
            "rgb": {
                "values": {
                    "r": 241,
                    "g": 236,
                    "b": 202
                }
            },
            "hsl": {
                "values": {
                    "h": 52,
                    "s": 58,
                    "l": 87
                }
            },
            "cmyk": {
                "values": {
                    "c": 0,
                    "m": 2,
                    "y": 16,
                    "k": 5
                }
            }
        },
        "description": "A very light, vibrant yellow with warm orange-yellow tones."
    }
]
