[
    {
        "unique-color-id": "9928048",
        "name": "Ginger Snap",
        "other-names": [
            {
                "name": "Ginger Snap",
                "source": {
                    "name": "Pantone",
                    "url": "http://www.pantone.com"
                }
            },
            {
                "name": "17-1418",
                "source": {
                    "name": "pantone-number",
                    "url": "http://www.pantone.com"
                }
            },
            {
                "name": "Peppered Pecan",
                "source": {
                    "name": "color.pizza",
                    "url": "https://github.com/meodai/color-names"
                }
            }
        ],
        "naming-source": "Pantone",
        "nickname": "",
        "color-family": "Orange Shades",
        "color-codes": {
            "hex": {
                "values": {
                    "r1": "9",
                    "r2": "7",
                    "g1": "7",
                    "g2": "D",
                    "b1": "7",
                    "b2": "0",
                    "a1": "0",
                    "a2": "0"
                }
            },
            "rgb": {
                "values": {
                    "r": 151,
                    "g": 125,
                    "b": 112
                }
            },
            "hsl": {
                "values": {
                    "h": 20,
                    "s": 16,
                    "l": 52
                }
            },
            "cmyk": {
                "values": {
                    "c": 0,
                    "m": 17,
                    "y": 26,
                    "k": 41
                }
            }
        },
        "description": "A medium, muted orange with warm red tones."
    }
]
