[
    {
        "unique-color-id": "9538703",
        "name": "Gull",
        "other-names": [
            {
                "name": "Gull",
                "source": {
                    "name": "Pantone",
                    "url": "http://www.pantone.com"
                }
            },
            {
                "name": "17-3802",
                "source": {
                    "name": "pantone-number",
                    "url": "http://www.pantone.com"
                }
            }
        ],
        "naming-source": "Pantone",
        "nickname": "",
        "color-family": "Grey Shades",
        "color-codes": {
            "hex": {
                "values": {
                    "r1": "9",
                    "r2": "1",
                    "g1": "8",
                    "g2": "C",
                    "b1": "8",
                    "b2": "F",
                    "a1": "0",
                    "a2": "0"
                }
            },
            "rgb": {
                "values": {
                    "r": 145,
                    "g": 140,
                    "b": 143
                }
            },
            "hsl": {
                "values": {
                    "h": 324,
                    "s": 2,
                    "l": 56
                }
            },
            "cmyk": {
                "values": {
                    "c": 0,
                    "m": 3,
                    "y": 1,
                    "k": 43
                }
            }
        },
        "description": "A medium-light, neutral grey."
    }
]
