[
    {
        "unique-color-id": "11962938",
        "name": "Harvest Gold",
        "other-names": [
            {
                "name": "Harvest Gold",
                "source": {
                    "name": "Pantone",
                    "url": "http://www.pantone.com"
                }
            },
            {
                "name": "16-0948",
                "source": {
                    "name": "pantone-number",
                    "url": "http://www.pantone.com"
                }
            },
            {
                "name": "Brass Yellow",
                "source": {
                    "name": "color.pizza",
                    "url": "https://github.com/meodai/color-names"
                }
            }
        ],
        "naming-source": "Pantone",
        "nickname": "",
        "color-family": "Orange Shades",
        "color-codes": {
            "hex": {
                "values": {
                    "r1": "B",
                    "r2": "6",
                    "g1": "8",
                    "g2": "A",
                    "b1": "3",
                    "b2": "A",
                    "a1": "0",
                    "a2": "0"
                }
            },
            "rgb": {
                "values": {
                    "r": 182,
                    "g": 138,
                    "b": 58
                }
            },
            "hsl": {
                "values": {
                    "h": 39,
                    "s": 52,
                    "l": 47
                }
            },
            "cmyk": {
                "values": {
                    "c": 0,
                    "m": 24,
                    "y": 68,
                    "k": 29
                }
            }
        },
        "description": "A medium, vibrant orange with warm orange-yellow tones."
    }
]
