[
    {
        "unique-color-id": "15157811",
        "name": "Mandarin Red",
        "other-names": [
            {
                "name": "Mandarin Red",
                "source": {
                    "name": "Pantone",
                    "url": "http://www.pantone.com"
                }
            },
            {
                "name": "17-1562",
                "source": {
                    "name": "pantone-number",
                    "url": "http://www.pantone.com"
                }
            },
            {
                "name": "Tomato Curry",
                "source": {
                    "name": "color.pizza",
                    "url": "https://github.com/meodai/color-names"
                }
            }
        ],
        "naming-source": "Pantone",
        "nickname": "",
        "color-family": "Red Shades",
        "color-codes": {
            "hex": {
                "values": {
                    "r1": "E",
                    "r2": "7",
                    "g1": "4",
                    "g2": "A",
                    "b1": "3",
                    "b2": "3",
                    "a1": "0",
                    "a2": "0"
                }
            },
            "rgb": {
                "values": {
                    "r": 231,
                    "g": 74,
                    "b": 51
                }
            },
            "hsl": {
                "values": {
                    "h": 8,
                    "s": 79,
                    "l": 55
                }
            },
            "cmyk": {
                "values": {
                    "c": 0,
                    "m": 68,
                    "y": 78,
                    "k": 9
                }
            }
        },
        "description": "A medium, highly saturated red with warm red tones."
    }
]
