[
    {
        "unique-color-id": "3814971",
        "name": "Obsidian",
        "other-names": [
            {
                "name": "Obsidian",
                "source": {
                    "name": "Pantone",
                    "url": "http://www.pantone.com"
                }
            },
            {
                "name": "19-3902",
                "source": {
                    "name": "pantone-number",
                    "url": "http://www.pantone.com"
                }
            },
            {
                "name": "Shiny Rubber",
                "source": {
                    "name": "color.pizza",
                    "url": "https://github.com/meodai/color-names"
                }
            }
        ],
        "naming-source": "Pantone",
        "nickname": "",
        "color-family": "Grey Shades",
        "color-codes": {
            "hex": {
                "values": {
                    "r1": "3",
                    "r2": "A",
                    "g1": "3",
                    "g2": "6",
                    "b1": "3",
                    "b2": "B",
                    "a1": "0",
                    "a2": "0"
                }
            },
            "rgb": {
                "values": {
                    "r": 58,
                    "g": 54,
                    "b": 59
                }
            },
            "hsl": {
                "values": {
                    "h": 288,
                    "s": 4,
                    "l": 22
                }
            },
            "cmyk": {
                "values": {
                    "c": 2,
                    "m": 8,
                    "y": 0,
                    "k": 77
                }
            }
        },
        "description": "A dark, neutral grey."
    }
]
