[
    {
        "unique-color-id": "15118225",
        "name": "Peach Nougat",
        "other-names": [
            {
                "name": "Peach Nougat",
                "source": {
                    "name": "Pantone",
                    "url": "http://www.pantone.com"
                }
            },
            {
                "name": "14-1220",
                "source": {
                    "name": "pantone-number",
                    "url": "http://www.pantone.com"
                }
            },
            {
                "name": "Hush Puppy",
                "source": {
                    "name": "color.pizza",
                    "url": "https://github.com/meodai/color-names"
                }
            }
        ],
        "naming-source": "Pantone",
        "nickname": "",
        "color-family": "Orange Shades",
        "color-codes": {
            "hex": {
                "values": {
                    "r1": "E",
                    "r2": "6",
                    "g1": "A",
                    "g2": "F",
                    "b1": "9",
                    "b2": "1",
                    "a1": "0",
                    "a2": "0"
                }
            },
            "rgb": {
                "values": {
                    "r": 230,
                    "g": 175,
                    "b": 145
                }
            },
            "hsl": {
                "values": {
                    "h": 21,
                    "s": 63,
                    "l": 74
                }
            },
            "cmyk": {
                "values": {
                    "c": 0,
                    "m": 24,
                    "y": 37,
                    "k": 10
                }
            }
        },
        "description": "A light, vibrant orange with warm red tones."
    }
]
