[
    {
        "unique-color-id": "8289672",
        "name": "Quicksilver",
        "other-names": [
            {
                "name": "Quicksilver",
                "source": {
                    "name": "Pantone",
                    "url": "http://www.pantone.com"
                }
            },
            {
                "name": "17-3907",
                "source": {
                    "name": "pantone-number",
                    "url": "http://www.pantone.com"
                }
            },
            {
                "name": "Silver Surfer",
                "source": {
                    "name": "color.pizza",
                    "url": "https://github.com/meodai/color-names"
                }
            }
        ],
        "naming-source": "Pantone",
        "nickname": "",
        "color-family": "Grey Shades",
        "color-codes": {
            "hex": {
                "values": {
                    "r1": "7",
                    "r2": "E",
                    "g1": "7",
                    "g2": "D",
                    "b1": "8",
                    "b2": "8",
                    "a1": "0",
                    "a2": "0"
                }
            },
            "rgb": {
                "values": {
                    "r": 126,
                    "g": 125,
                    "b": 136
                }
            },
            "hsl": {
                "values": {
                    "h": 245,
                    "s": 4,
                    "l": 51
                }
            },
            "cmyk": {
                "values": {
                    "c": 7,
                    "m": 8,
                    "y": 0,
                    "k": 47
                }
            }
        },
        "description": "A medium, neutral grey."
    }
]
