[
    {
        "unique-color-id": "11245717",
        "name": "Sphinx",
        "other-names": [
            {
                "name": "Sphinx",
                "source": {
                    "name": "Pantone",
                    "url": "http://www.pantone.com"
                }
            },
            {
                "name": "16-1703",
                "source": {
                    "name": "pantone-number",
                    "url": "http://www.pantone.com"
                }
            },
            {
                "name": "Smoky Sunrise",
                "source": {
                    "name": "color.pizza",
                    "url": "https://github.com/meodai/color-names"
                }
            }
        ],
        "naming-source": "Pantone",
        "nickname": "",
        "color-family": "Red Shades",
        "color-codes": {
            "hex": {
                "values": {
                    "r1": "A",
                    "r2": "B",
                    "g1": "9",
                    "g2": "8",
                    "b1": "9",
                    "b2": "5",
                    "a1": "0",
                    "a2": "0"
                }
            },
            "rgb": {
                "values": {
                    "r": 171,
                    "g": 152,
                    "b": 149
                }
            },
            "hsl": {
                "values": {
                    "h": 8,
                    "s": 12,
                    "l": 63
                }
            },
            "cmyk": {
                "values": {
                    "c": 0,
                    "m": 11,
                    "y": 13,
                    "k": 33
                }
            }
        },
        "description": "A medium-light, muted red with warm red tones."
    }
]
