[
    {
        "unique-color-id": "13665092",
        "name": "Topaz",
        "other-names": [
            {
                "name": "Topaz",
                "source": {
                    "name": "Pantone",
                    "url": "http://www.pantone.com"
                }
            },
            {
                "name": "16-1150",
                "source": {
                    "name": "pantone-number",
                    "url": "http://www.pantone.com"
                }
            },
            {
                "name": "Melted Copper",
                "source": {
                    "name": "color.pizza",
                    "url": "https://github.com/meodai/color-names"
                }
            }
        ],
        "naming-source": "Pantone",
        "nickname": "",
        "color-family": "Orange Shades",
        "color-codes": {
            "hex": {
                "values": {
                    "r1": "D",
                    "r2": "0",
                    "g1": "8",
                    "g2": "3",
                    "b1": "4",
                    "b2": "4",
                    "a1": "0",
                    "a2": "0"
                }
            },
            "rgb": {
                "values": {
                    "r": 208,
                    "g": 131,
                    "b": 68
                }
            },
            "hsl": {
                "values": {
                    "h": 27,
                    "s": 60,
                    "l": 54
                }
            },
            "cmyk": {
                "values": {
                    "c": 0,
                    "m": 37,
                    "y": 67,
                    "k": 18
                }
            }
        },
        "description": "A medium, vibrant orange with warm red tones."
    }
]
